{
  "id": "/project/Tuxedo-Cupcakes/src/components/Navbar/Navbar.module.scss",
  "deps": [],
  "plugins": [
    "__load__",
    "vite:css",
    "vite:css-post",
    "vite:import-analysis"
  ],
  "transforms": [
    {
      "name": "__load__",
      "result": "@use '../../global-styles/variables.scss' as *;\n\n.head {\n  margin-top: calc(2 * $ru);\n  display: flex;\n  align-items: center;\n  flex-direction: column;\n  user-select: none;\n\n  nav {\n    display: flex;\n    align-items: center;\n    flex-direction: row;\n    column-gap: calc(5 * $tru);\n    padding-bottom: calc(3 * $ru);\n    width: calc(95 * $ru);\n\n    @media (max-width: 700px) {\n      display: grid;\n      grid-template-columns: repeat(2, 1fr);\n      height: calc(3 * $ru);\n      width: 100%;\n      min-height: calc(10 * $tru);\n    }\n\n    a {\n      font-size: calc(3 * $tru);\n      font-weight: 500;\n      color: $cyan;\n      text-decoration: none;\n      text-align: center;\n      transition: color 0.2s ease-out;\n    }\n    a:hover {\n      color: $darkCyan;\n    }\n    a.selectedTab {\n      color: $darkCyan;\n      cursor: default;\n    }\n  }\n\n  a.selectedTab {\n    cursor: default;\n  }\n}\n\n.logo {\n  &.bigLogo {\n    width: calc($ru * 60);\n    padding: calc($ru * 3);\n  }\n\n  &.smallLogo {\n    width: calc($ru * 30);\n    padding-bottom: calc($ru * 1.5);\n    padding-top: calc($ru * 0.5);\n  }\n\n  &.toBigLogo {\n    animation: grow 0.3s ease-out forwards;\n  }\n\n  @keyframes grow {\n    from {\n      width: calc($ru * 30);\n      padding-bottom: calc($ru * 1.5);\n      padding-top: calc($ru * 0.5);\n    }\n    to {\n      width: calc($ru * 60);\n      padding-top: calc($ru * 3);\n      padding-bottom: calc($ru * 3);\n    }\n  }\n\n  &.toSmallLogo {\n    animation: shrink 0.3s ease-out forwards;\n  }\n\n  @keyframes shrink {\n    from {\n      width: calc($ru * 60);\n      padding-top: calc($ru * 3);\n      padding-bottom: calc($ru * 3);\n    }\n    to {\n      width: calc($ru * 30);\n      padding-bottom: calc($ru * 1.5);\n      padding-top: calc($ru * 0.5);\n    }\n  }\n}\n\n.decoration {\n  width: calc(90 * $ru);\n\n  &.bigLogo {\n    transform: translateY(0);\n    width: calc(90 * $ru);\n  }\n\n  &.smallLogo {\n    transform: translateY(calc(-5 * $ru));\n    width: 0;\n  }\n\n  &.toBigLogo {\n    animation: slideIn 0.3s ease-out forwards;\n  }\n\n  @keyframes slideIn {\n    from {\n      transform: translateY(calc(-5 * $ru));\n      width: 0;\n    }\n    to {\n      transform: translateY(0);\n      width: calc(90 * $ru);\n    }\n  }\n\n  &.toSmallLogo {\n    animation: slideOut 0.3s ease-out forwards;\n  }\n\n  @keyframes slideOut {\n    from {\n      transform: translateY(0);\n      width: calc(90 * $ru);\n    }\n    to {\n      transform: translateY(calc(-5 * $ru));\n      width: 0;\n    }\n  }\n}\n\n.fadeIn {\n  opacity: 0;\n  animation: fadeIn 1s ease-in forwards;\n}\n\n@keyframes fadeIn {\n  from {\n    opacity: 0%;\n  }\n  to {\n    opacity: 100%;\n  }\n}\n\n.fadeOut {\n  opacity: 100%;\n  animation: fadeOut 1s ease-in forwards;\n}\n\n@keyframes fadeOut {\n  from {\n    opacity: 100%;\n  }\n  to {\n    opacity: 0%;\n  }\n}\n",
      "start": 1669682803034,
      "end": 1669682803034
    },
    {
      "name": "vite:css",
      "result": "._head_iotf2_1 {\n  margin-top: calc(2 * min(90vw, min(60vw + 300px, 1200px))/100);\n  display: flex;\n  align-items: center;\n  flex-direction: column;\n  user-select: none;\n}\n._head_iotf2_1 nav {\n  display: flex;\n  align-items: center;\n  flex-direction: row;\n  column-gap: calc(5 * min(90vw + 200px, min(60vw + 400px, 1200px))/100);\n  padding-bottom: calc(3 * min(90vw, min(60vw + 300px, 1200px))/100);\n  width: calc(95 * min(90vw, min(60vw + 300px, 1200px))/100);\n}\n@media (max-width: 700px) {\n  ._head_iotf2_1 nav {\n    display: grid;\n    grid-template-columns: repeat(2, 1fr);\n    height: calc(3 * min(90vw, min(60vw + 300px, 1200px))/100);\n    width: 100%;\n    min-height: calc(10 * min(90vw + 200px, min(60vw + 400px, 1200px))/100);\n  }\n}\n._head_iotf2_1 nav a {\n  font-size: calc(3 * min(90vw + 200px, min(60vw + 400px, 1200px))/100);\n  font-weight: 500;\n  color: #4aa1b4;\n  text-decoration: none;\n  text-align: center;\n  transition: color 0.2s ease-out;\n}\n._head_iotf2_1 nav a:hover {\n  color: #407682;\n}\n._head_iotf2_1 nav a._selectedTab_iotf2_36 {\n  color: #407682;\n  cursor: default;\n}\n._head_iotf2_1 a._selectedTab_iotf2_36 {\n  cursor: default;\n}\n\n._logo_iotf2_44._bigLogo_iotf2_44 {\n  width: calc(min(90vw, min(60vw + 300px, 1200px))/100 * 60);\n  padding: calc(min(90vw, min(60vw + 300px, 1200px))/100 * 3);\n}\n._logo_iotf2_44._smallLogo_iotf2_48 {\n  width: calc(min(90vw, min(60vw + 300px, 1200px))/100 * 30);\n  padding-bottom: calc(min(90vw, min(60vw + 300px, 1200px))/100 * 1.5);\n  padding-top: calc(min(90vw, min(60vw + 300px, 1200px))/100 * 0.5);\n}\n._logo_iotf2_44._toBigLogo_iotf2_53 {\n  animation: _grow_iotf2_1 0.3s ease-out forwards;\n}\n@keyframes _grow_iotf2_1 {\n  from {\n    width: calc(min(90vw, min(60vw + 300px, 1200px))/100 * 30);\n    padding-bottom: calc(min(90vw, min(60vw + 300px, 1200px))/100 * 1.5);\n    padding-top: calc(min(90vw, min(60vw + 300px, 1200px))/100 * 0.5);\n  }\n  to {\n    width: calc(min(90vw, min(60vw + 300px, 1200px))/100 * 60);\n    padding-top: calc(min(90vw, min(60vw + 300px, 1200px))/100 * 3);\n    padding-bottom: calc(min(90vw, min(60vw + 300px, 1200px))/100 * 3);\n  }\n}\n._logo_iotf2_44._toSmallLogo_iotf2_68 {\n  animation: _shrink_iotf2_1 0.3s ease-out forwards;\n}\n@keyframes _shrink_iotf2_1 {\n  from {\n    width: calc(min(90vw, min(60vw + 300px, 1200px))/100 * 60);\n    padding-top: calc(min(90vw, min(60vw + 300px, 1200px))/100 * 3);\n    padding-bottom: calc(min(90vw, min(60vw + 300px, 1200px))/100 * 3);\n  }\n  to {\n    width: calc(min(90vw, min(60vw + 300px, 1200px))/100 * 30);\n    padding-bottom: calc(min(90vw, min(60vw + 300px, 1200px))/100 * 1.5);\n    padding-top: calc(min(90vw, min(60vw + 300px, 1200px))/100 * 0.5);\n  }\n}\n\n._decoration_iotf2_84 {\n  width: calc(90 * min(90vw, min(60vw + 300px, 1200px))/100);\n}\n._decoration_iotf2_84._bigLogo_iotf2_44 {\n  transform: translateY(0);\n  width: calc(90 * min(90vw, min(60vw + 300px, 1200px))/100);\n}\n._decoration_iotf2_84._smallLogo_iotf2_48 {\n  transform: translateY(calc(-5 * min(90vw, min(60vw + 300px, 1200px))/100));\n  width: 0;\n}\n._decoration_iotf2_84._toBigLogo_iotf2_53 {\n  animation: _slideIn_iotf2_1 0.3s ease-out forwards;\n}\n@keyframes _slideIn_iotf2_1 {\n  from {\n    transform: translateY(calc(-5 * min(90vw, min(60vw + 300px, 1200px))/100));\n    width: 0;\n  }\n  to {\n    transform: translateY(0);\n    width: calc(90 * min(90vw, min(60vw + 300px, 1200px))/100);\n  }\n}\n._decoration_iotf2_84._toSmallLogo_iotf2_68 {\n  animation: _slideOut_iotf2_1 0.3s ease-out forwards;\n}\n@keyframes _slideOut_iotf2_1 {\n  from {\n    transform: translateY(0);\n    width: calc(90 * min(90vw, min(60vw + 300px, 1200px))/100);\n  }\n  to {\n    transform: translateY(calc(-5 * min(90vw, min(60vw + 300px, 1200px))/100));\n    width: 0;\n  }\n}\n\n._fadeIn_iotf2_122 {\n  opacity: 0;\n  animation: _fadeIn_iotf2_122 1s ease-in forwards;\n}\n\n@keyframes _fadeIn_iotf2_122 {\n  from {\n    opacity: 0%;\n  }\n  to {\n    opacity: 100%;\n  }\n}\n._fadeOut_iotf2_135 {\n  opacity: 100%;\n  animation: _fadeOut_iotf2_135 1s ease-in forwards;\n}\n\n@keyframes _fadeOut_iotf2_135 {\n  from {\n    opacity: 100%;\n  }\n  to {\n    opacity: 0%;\n  }\n}",
      "start": 1669682803034,
      "end": 1669682803058
    },
    {
      "name": "vite:css-post",
      "result": "import { updateStyle as __vite__updateStyle, removeStyle as __vite__removeStyle } from \"/@vite/client\"\nconst __vite__id = \"/project/Tuxedo-Cupcakes/src/components/Navbar/Navbar.module.scss\"\nconst __vite__css = \"._head_iotf2_1 {\\n  margin-top: calc(2 * min(90vw, min(60vw + 300px, 1200px))/100);\\n  display: flex;\\n  align-items: center;\\n  flex-direction: column;\\n  user-select: none;\\n}\\n._head_iotf2_1 nav {\\n  display: flex;\\n  align-items: center;\\n  flex-direction: row;\\n  column-gap: calc(5 * min(90vw + 200px, min(60vw + 400px, 1200px))/100);\\n  padding-bottom: calc(3 * min(90vw, min(60vw + 300px, 1200px))/100);\\n  width: calc(95 * min(90vw, min(60vw + 300px, 1200px))/100);\\n}\\n@media (max-width: 700px) {\\n  ._head_iotf2_1 nav {\\n    display: grid;\\n    grid-template-columns: repeat(2, 1fr);\\n    height: calc(3 * min(90vw, min(60vw + 300px, 1200px))/100);\\n    width: 100%;\\n    min-height: calc(10 * min(90vw + 200px, min(60vw + 400px, 1200px))/100);\\n  }\\n}\\n._head_iotf2_1 nav a {\\n  font-size: calc(3 * min(90vw + 200px, min(60vw + 400px, 1200px))/100);\\n  font-weight: 500;\\n  color: #4aa1b4;\\n  text-decoration: none;\\n  text-align: center;\\n  transition: color 0.2s ease-out;\\n}\\n._head_iotf2_1 nav a:hover {\\n  color: #407682;\\n}\\n._head_iotf2_1 nav a._selectedTab_iotf2_36 {\\n  color: #407682;\\n  cursor: default;\\n}\\n._head_iotf2_1 a._selectedTab_iotf2_36 {\\n  cursor: default;\\n}\\n\\n._logo_iotf2_44._bigLogo_iotf2_44 {\\n  width: calc(min(90vw, min(60vw + 300px, 1200px))/100 * 60);\\n  padding: calc(min(90vw, min(60vw + 300px, 1200px))/100 * 3);\\n}\\n._logo_iotf2_44._smallLogo_iotf2_48 {\\n  width: calc(min(90vw, min(60vw + 300px, 1200px))/100 * 30);\\n  padding-bottom: calc(min(90vw, min(60vw + 300px, 1200px))/100 * 1.5);\\n  padding-top: calc(min(90vw, min(60vw + 300px, 1200px))/100 * 0.5);\\n}\\n._logo_iotf2_44._toBigLogo_iotf2_53 {\\n  animation: _grow_iotf2_1 0.3s ease-out forwards;\\n}\\n@keyframes _grow_iotf2_1 {\\n  from {\\n    width: calc(min(90vw, min(60vw + 300px, 1200px))/100 * 30);\\n    padding-bottom: calc(min(90vw, min(60vw + 300px, 1200px))/100 * 1.5);\\n    padding-top: calc(min(90vw, min(60vw + 300px, 1200px))/100 * 0.5);\\n  }\\n  to {\\n    width: calc(min(90vw, min(60vw + 300px, 1200px))/100 * 60);\\n    padding-top: calc(min(90vw, min(60vw + 300px, 1200px))/100 * 3);\\n    padding-bottom: calc(min(90vw, min(60vw + 300px, 1200px))/100 * 3);\\n  }\\n}\\n._logo_iotf2_44._toSmallLogo_iotf2_68 {\\n  animation: _shrink_iotf2_1 0.3s ease-out forwards;\\n}\\n@keyframes _shrink_iotf2_1 {\\n  from {\\n    width: calc(min(90vw, min(60vw + 300px, 1200px))/100 * 60);\\n    padding-top: calc(min(90vw, min(60vw + 300px, 1200px))/100 * 3);\\n    padding-bottom: calc(min(90vw, min(60vw + 300px, 1200px))/100 * 3);\\n  }\\n  to {\\n    width: calc(min(90vw, min(60vw + 300px, 1200px))/100 * 30);\\n    padding-bottom: calc(min(90vw, min(60vw + 300px, 1200px))/100 * 1.5);\\n    padding-top: calc(min(90vw, min(60vw + 300px, 1200px))/100 * 0.5);\\n  }\\n}\\n\\n._decoration_iotf2_84 {\\n  width: calc(90 * min(90vw, min(60vw + 300px, 1200px))/100);\\n}\\n._decoration_iotf2_84._bigLogo_iotf2_44 {\\n  transform: translateY(0);\\n  width: calc(90 * min(90vw, min(60vw + 300px, 1200px))/100);\\n}\\n._decoration_iotf2_84._smallLogo_iotf2_48 {\\n  transform: translateY(calc(-5 * min(90vw, min(60vw + 300px, 1200px))/100));\\n  width: 0;\\n}\\n._decoration_iotf2_84._toBigLogo_iotf2_53 {\\n  animation: _slideIn_iotf2_1 0.3s ease-out forwards;\\n}\\n@keyframes _slideIn_iotf2_1 {\\n  from {\\n    transform: translateY(calc(-5 * min(90vw, min(60vw + 300px, 1200px))/100));\\n    width: 0;\\n  }\\n  to {\\n    transform: translateY(0);\\n    width: calc(90 * min(90vw, min(60vw + 300px, 1200px))/100);\\n  }\\n}\\n._decoration_iotf2_84._toSmallLogo_iotf2_68 {\\n  animation: _slideOut_iotf2_1 0.3s ease-out forwards;\\n}\\n@keyframes _slideOut_iotf2_1 {\\n  from {\\n    transform: translateY(0);\\n    width: calc(90 * min(90vw, min(60vw + 300px, 1200px))/100);\\n  }\\n  to {\\n    transform: translateY(calc(-5 * min(90vw, min(60vw + 300px, 1200px))/100));\\n    width: 0;\\n  }\\n}\\n\\n._fadeIn_iotf2_122 {\\n  opacity: 0;\\n  animation: _fadeIn_iotf2_122 1s ease-in forwards;\\n}\\n\\n@keyframes _fadeIn_iotf2_122 {\\n  from {\\n    opacity: 0%;\\n  }\\n  to {\\n    opacity: 100%;\\n  }\\n}\\n._fadeOut_iotf2_135 {\\n  opacity: 100%;\\n  animation: _fadeOut_iotf2_135 1s ease-in forwards;\\n}\\n\\n@keyframes _fadeOut_iotf2_135 {\\n  from {\\n    opacity: 100%;\\n  }\\n  to {\\n    opacity: 0%;\\n  }\\n}\"\n__vite__updateStyle(__vite__id, __vite__css)\nexport const head = \"_head_iotf2_1\";\nexport const selectedTab = \"_selectedTab_iotf2_36\";\nexport const logo = \"_logo_iotf2_44\";\nexport const bigLogo = \"_bigLogo_iotf2_44\";\nexport const smallLogo = \"_smallLogo_iotf2_48\";\nexport const toBigLogo = \"_toBigLogo_iotf2_53\";\nexport const grow = \"_grow_iotf2_1\";\nexport const toSmallLogo = \"_toSmallLogo_iotf2_68\";\nexport const shrink = \"_shrink_iotf2_1\";\nexport const decoration = \"_decoration_iotf2_84\";\nexport const slideIn = \"_slideIn_iotf2_1\";\nexport const slideOut = \"_slideOut_iotf2_1\";\nexport const fadeIn = \"_fadeIn_iotf2_122\";\nexport const fadeOut = \"_fadeOut_iotf2_135\";\nexport default {\n\thead: head,\n\tselectedTab: selectedTab,\n\tlogo: logo,\n\tbigLogo: bigLogo,\n\tsmallLogo: smallLogo,\n\ttoBigLogo: toBigLogo,\n\tgrow: grow,\n\ttoSmallLogo: toSmallLogo,\n\tshrink: shrink,\n\tdecoration: decoration,\n\tslideIn: slideIn,\n\tslideOut: slideOut,\n\tfadeIn: fadeIn,\n\tfadeOut: fadeOut\n};\n\nimport.meta.hot.prune(() => __vite__removeStyle(__vite__id))",
      "start": 1669682803058,
      "end": 1669682803058
    },
    {
      "name": "vite:import-analysis",
      "result": "import { createHotContext as __vite__createHotContext } from \"/@vite/client\";import.meta.hot = __vite__createHotContext(\"/src/components/Navbar/Navbar.module.scss\");import { updateStyle as __vite__updateStyle, removeStyle as __vite__removeStyle } from \"/@vite/client\"\nconst __vite__id = \"/project/Tuxedo-Cupcakes/src/components/Navbar/Navbar.module.scss\"\nconst __vite__css = \"._head_iotf2_1 {\\n  margin-top: calc(2 * min(90vw, min(60vw + 300px, 1200px))/100);\\n  display: flex;\\n  align-items: center;\\n  flex-direction: column;\\n  user-select: none;\\n}\\n._head_iotf2_1 nav {\\n  display: flex;\\n  align-items: center;\\n  flex-direction: row;\\n  column-gap: calc(5 * min(90vw + 200px, min(60vw + 400px, 1200px))/100);\\n  padding-bottom: calc(3 * min(90vw, min(60vw + 300px, 1200px))/100);\\n  width: calc(95 * min(90vw, min(60vw + 300px, 1200px))/100);\\n}\\n@media (max-width: 700px) {\\n  ._head_iotf2_1 nav {\\n    display: grid;\\n    grid-template-columns: repeat(2, 1fr);\\n    height: calc(3 * min(90vw, min(60vw + 300px, 1200px))/100);\\n    width: 100%;\\n    min-height: calc(10 * min(90vw + 200px, min(60vw + 400px, 1200px))/100);\\n  }\\n}\\n._head_iotf2_1 nav a {\\n  font-size: calc(3 * min(90vw + 200px, min(60vw + 400px, 1200px))/100);\\n  font-weight: 500;\\n  color: #4aa1b4;\\n  text-decoration: none;\\n  text-align: center;\\n  transition: color 0.2s ease-out;\\n}\\n._head_iotf2_1 nav a:hover {\\n  color: #407682;\\n}\\n._head_iotf2_1 nav a._selectedTab_iotf2_36 {\\n  color: #407682;\\n  cursor: default;\\n}\\n._head_iotf2_1 a._selectedTab_iotf2_36 {\\n  cursor: default;\\n}\\n\\n._logo_iotf2_44._bigLogo_iotf2_44 {\\n  width: calc(min(90vw, min(60vw + 300px, 1200px))/100 * 60);\\n  padding: calc(min(90vw, min(60vw + 300px, 1200px))/100 * 3);\\n}\\n._logo_iotf2_44._smallLogo_iotf2_48 {\\n  width: calc(min(90vw, min(60vw + 300px, 1200px))/100 * 30);\\n  padding-bottom: calc(min(90vw, min(60vw + 300px, 1200px))/100 * 1.5);\\n  padding-top: calc(min(90vw, min(60vw + 300px, 1200px))/100 * 0.5);\\n}\\n._logo_iotf2_44._toBigLogo_iotf2_53 {\\n  animation: _grow_iotf2_1 0.3s ease-out forwards;\\n}\\n@keyframes _grow_iotf2_1 {\\n  from {\\n    width: calc(min(90vw, min(60vw + 300px, 1200px))/100 * 30);\\n    padding-bottom: calc(min(90vw, min(60vw + 300px, 1200px))/100 * 1.5);\\n    padding-top: calc(min(90vw, min(60vw + 300px, 1200px))/100 * 0.5);\\n  }\\n  to {\\n    width: calc(min(90vw, min(60vw + 300px, 1200px))/100 * 60);\\n    padding-top: calc(min(90vw, min(60vw + 300px, 1200px))/100 * 3);\\n    padding-bottom: calc(min(90vw, min(60vw + 300px, 1200px))/100 * 3);\\n  }\\n}\\n._logo_iotf2_44._toSmallLogo_iotf2_68 {\\n  animation: _shrink_iotf2_1 0.3s ease-out forwards;\\n}\\n@keyframes _shrink_iotf2_1 {\\n  from {\\n    width: calc(min(90vw, min(60vw + 300px, 1200px))/100 * 60);\\n    padding-top: calc(min(90vw, min(60vw + 300px, 1200px))/100 * 3);\\n    padding-bottom: calc(min(90vw, min(60vw + 300px, 1200px))/100 * 3);\\n  }\\n  to {\\n    width: calc(min(90vw, min(60vw + 300px, 1200px))/100 * 30);\\n    padding-bottom: calc(min(90vw, min(60vw + 300px, 1200px))/100 * 1.5);\\n    padding-top: calc(min(90vw, min(60vw + 300px, 1200px))/100 * 0.5);\\n  }\\n}\\n\\n._decoration_iotf2_84 {\\n  width: calc(90 * min(90vw, min(60vw + 300px, 1200px))/100);\\n}\\n._decoration_iotf2_84._bigLogo_iotf2_44 {\\n  transform: translateY(0);\\n  width: calc(90 * min(90vw, min(60vw + 300px, 1200px))/100);\\n}\\n._decoration_iotf2_84._smallLogo_iotf2_48 {\\n  transform: translateY(calc(-5 * min(90vw, min(60vw + 300px, 1200px))/100));\\n  width: 0;\\n}\\n._decoration_iotf2_84._toBigLogo_iotf2_53 {\\n  animation: _slideIn_iotf2_1 0.3s ease-out forwards;\\n}\\n@keyframes _slideIn_iotf2_1 {\\n  from {\\n    transform: translateY(calc(-5 * min(90vw, min(60vw + 300px, 1200px))/100));\\n    width: 0;\\n  }\\n  to {\\n    transform: translateY(0);\\n    width: calc(90 * min(90vw, min(60vw + 300px, 1200px))/100);\\n  }\\n}\\n._decoration_iotf2_84._toSmallLogo_iotf2_68 {\\n  animation: _slideOut_iotf2_1 0.3s ease-out forwards;\\n}\\n@keyframes _slideOut_iotf2_1 {\\n  from {\\n    transform: translateY(0);\\n    width: calc(90 * min(90vw, min(60vw + 300px, 1200px))/100);\\n  }\\n  to {\\n    transform: translateY(calc(-5 * min(90vw, min(60vw + 300px, 1200px))/100));\\n    width: 0;\\n  }\\n}\\n\\n._fadeIn_iotf2_122 {\\n  opacity: 0;\\n  animation: _fadeIn_iotf2_122 1s ease-in forwards;\\n}\\n\\n@keyframes _fadeIn_iotf2_122 {\\n  from {\\n    opacity: 0%;\\n  }\\n  to {\\n    opacity: 100%;\\n  }\\n}\\n._fadeOut_iotf2_135 {\\n  opacity: 100%;\\n  animation: _fadeOut_iotf2_135 1s ease-in forwards;\\n}\\n\\n@keyframes _fadeOut_iotf2_135 {\\n  from {\\n    opacity: 100%;\\n  }\\n  to {\\n    opacity: 0%;\\n  }\\n}\"\n__vite__updateStyle(__vite__id, __vite__css)\nexport const head = \"_head_iotf2_1\";\nexport const selectedTab = \"_selectedTab_iotf2_36\";\nexport const logo = \"_logo_iotf2_44\";\nexport const bigLogo = \"_bigLogo_iotf2_44\";\nexport const smallLogo = \"_smallLogo_iotf2_48\";\nexport const toBigLogo = \"_toBigLogo_iotf2_53\";\nexport const grow = \"_grow_iotf2_1\";\nexport const toSmallLogo = \"_toSmallLogo_iotf2_68\";\nexport const shrink = \"_shrink_iotf2_1\";\nexport const decoration = \"_decoration_iotf2_84\";\nexport const slideIn = \"_slideIn_iotf2_1\";\nexport const slideOut = \"_slideOut_iotf2_1\";\nexport const fadeIn = \"_fadeIn_iotf2_122\";\nexport const fadeOut = \"_fadeOut_iotf2_135\";\nexport default {\n\thead: head,\n\tselectedTab: selectedTab,\n\tlogo: logo,\n\tbigLogo: bigLogo,\n\tsmallLogo: smallLogo,\n\ttoBigLogo: toBigLogo,\n\tgrow: grow,\n\ttoSmallLogo: toSmallLogo,\n\tshrink: shrink,\n\tdecoration: decoration,\n\tslideIn: slideIn,\n\tslideOut: slideOut,\n\tfadeIn: fadeIn,\n\tfadeOut: fadeOut\n};\n\nimport.meta.hot.prune(() => __vite__removeStyle(__vite__id))",
      "start": 1669682803058,
      "end": 1669682803058
    }
  ],
  "virtual": false
}